{
  "characteristics": {}, 
  "choices": {
    "cmd_key": "default", 
    "compile_type": "dynamic", 
    "compiler_vars": {
      "HOG4X4": ""
    }, 
    "cpu_freq": "max", 
    "data_uoa": "realeyes-hog-opencl-tbb", 
    "dataset_uoa": "image-jpeg-0001", 
    "device_id": "", 
    "energy": "no", 
    "gpu_freq": "max", 
    "host_os": "windows-64", 
    "module_uoa": "b0ac08fe1d3c2615", 
    "target_os": "windows-64", 
    "target_os_bits": "64"
  }, 
  "choices_desc": {
    "##compiler_env_uoa": {
      "choices": [
        "289842d618a4e54a", 
        "924e05b4e11f9dcc", 
        "94e0f4653b0fe9fa", 
        "ac64c238d32a89b3", 
        "b90ce949dca060c0", 
        "ba51adfd437ab8de", 
        "d1cad28a354152b3"
      ], 
      "has_choice": "yes", 
      "sort": 2000, 
      "type": "uoa"
    }, 
    "##compiler_flags#base_opt": {
      "choice": [
        "-O3", 
        "-fast", 
        "-O0", 
        "-O1", 
        "-O2", 
        "-Os"
      ], 
      "default": "", 
      "desc": "base compiler flag", 
      "sort": 10000, 
      "tags": [
        "base", 
        "basic", 
        "optimization"
      ], 
      "type": "text"
    }, 
    "##compiler_flags#global_loop_unrolling": {
      "can_omit": "yes", 
      "default": "", 
      "desc": "compiler flag: -Qunroll", 
      "explore_prefix": "-Qunroll", 
      "explore_start": 1, 
      "explore_step": 1, 
      "explore_stop": 32, 
      "sort": 10100, 
      "tags": [
        "basic", 
        "optimization"
      ], 
      "type": "integer"
    }, 
    "##compiler_flags#openmp": {
      "can_omit": "yes", 
      "choice": [
        "-openmp", 
        ""
      ], 
      "default": "", 
      "desc": "compiler flag: openmp", 
      "sort": 10001, 
      "tags": [
        "basic", 
        "openmp", 
        "optimization"
      ], 
      "type": "text"
    }, 
    "##dataset_uoa": {
      "choices": [
        "f994f708cc102713", 
        "1aaaa23c44e588f9", 
        "21500da03e4ccfa3", 
        "4070a925b6077f3c", 
        "3821f8b25917cab0", 
        "ff6a34d62a55c85b", 
        "b8a5e9fe4d94a468", 
        "ed469fdd4a37bd88", 
        "51694ca9764d88b7", 
        "3fe364dc4d218734", 
        "ce947b2b6233bdfa", 
        "1a169bc4b8baaddc", 
        "44ca5ab7a268cf4d", 
        "4e64ecddc481c8dd", 
        "bf5d476534f04885", 
        "b41491866f4f4ce8", 
        "481066c6404d96b7", 
        "38cfe7c67cec0612", 
        "c59c2aab21a48a29", 
        "9ddbbe02281b6d13", 
        "65d42f68279f6b63", 
        "24b4e8d89ff3cc85", 
        "96fdd91703544877", 
        "c1242929d23e4899", 
        "bf8554677900d79e", 
        "2b8f9d53789948f6", 
        "ab3453cad8a007bc", 
        "175c91c2e97845a5", 
        "8df77b462ea8b0a3", 
        "bd7b4b0a8ff44d45", 
        "5458e41669da5482", 
        "4dfb81be6aa11ece", 
        "3da4b4444db6588f", 
        "406b4c40b3854b42", 
        "eb0c3b428c284c33"
      ], 
      "has_choice": "yes", 
      "sort": 1200, 
      "tags": [
        "setup", 
        "dataset"
      ], 
      "type": "uoa"
    }, 
    "##env#CT_REPEAT_MAIN": {
      "default": 1, 
      "desc": "Main function/kernel repetition", 
      "explore_start": 1, 
      "explore_step": 10, 
      "explore_stop": 1000000, 
      "sort": 1, 
      "type": "integer"
    }
  }, 
  "dependencies": {
    "compiler": {
      "bat": "call D:\\Work1\\CK\\ck-repos\\fgg-local-win\\env\\289842d618a4e54a\\env.bat\n", 
      "build_dir_name": "icc", 
      "choices": [
        "289842d618a4e54a", 
        "924e05b4e11f9dcc", 
        "94e0f4653b0fe9fa", 
        "ac64c238d32a89b3", 
        "b90ce949dca060c0", 
        "ba51adfd437ab8de", 
        "d1cad28a354152b3"
      ], 
      "cus": {
        "build-dir-name": "icc", 
        "build_dir_name": "icc", 
        "env_prefix": "CK_ENV_COMPILER_ICC", 
        "extra_dir": "", 
        "languages": [
          "C", 
          "CPP", 
          "F77", 
          "F90", 
          "F95"
        ], 
        "path_install": "C:\\Program Files (x86)\\Intel\\Composer XE 2015", 
        "retarget": "", 
        "skip_add_to_bin": "yes", 
        "skip_add_to_ld_path": "yes", 
        "skip_add_to_path": "yes", 
        "tool_prefix": "", 
        "version": "2015", 
        "version_int": 2015
      }, 
      "dict": {
        "customize": {
          "build-dir-name": "icc", 
          "build_dir_name": "icc", 
          "env_prefix": "CK_ENV_COMPILER_ICC", 
          "extra_dir": "", 
          "languages": [
            "C", 
            "CPP", 
            "F77", 
            "F90", 
            "F95"
          ], 
          "path_install": "C:\\Program Files (x86)\\Intel\\Composer XE 2015", 
          "retarget": "", 
          "skip_add_to_bin": "yes", 
          "skip_add_to_ld_path": "yes", 
          "skip_add_to_path": "yes", 
          "tool_prefix": "", 
          "version": "2015", 
          "version_int": 2015
        }, 
        "deps": {
          "compiler_mcl": {
            "bat": "call D:\\Work1\\CK\\ck-repos\\fgg-local-win\\env\\924e05b4e11f9dcc\\env.bat\n", 
            "build_dir_name": "mcl", 
            "dict": {
              "customize": {
                "add_win_sdk_path": "yes", 
                "build-dir-name": "mcl", 
                "build_dir_name": "mcl", 
                "env_prefix": "CK_ENV_COMPILER_MVSC", 
                "extra_dir": "", 
                "input_path_example": "C:\\Program Files (x86)\\Microsoft Visual Studio 9.0\\VC", 
                "languages": [
                  "C", 
                  "CPP"
                ], 
                "path_install": "C:\\Program Files (x86)\\Microsoft Visual Studio 12.0\\VC", 
                "retarget": "", 
                "skip_add_to_bin": "yes", 
                "skip_add_to_ld_path": "yes", 
                "skip_add_to_path": "yes", 
                "tool_prefix": "", 
                "version": "18.00", 
                "version_int": 1800
              }, 
              "deps": {}, 
              "env": {
                "CK_AR": "lib", 
                "CK_ASM_EXT": ".asm", 
                "CK_CC": "cl", 
                "CK_COMPILER_FLAGS_OBLIGATORY": "/DWINDOWS /GS-", 
                "CK_COMPILER_FLAG_CPP11": "/Qstd=c++11", 
                "CK_COMPILER_FLAG_OPENMP": "/openmp", 
                "CK_COMPILER_FLAG_PTHREAD_LIB": "/pthread", 
                "CK_COMPILER_FLAG_STD90": "/Qstd=c90", 
                "CK_COMPILER_FLAG_STD99": "/Qstd=c99", 
                "CK_CXX": "cl", 
                "CK_DLL_EXT": ".dll", 
                "CK_EXE_EXT": ".exe", 
                "CK_FLAGS_CREATE_ASM": "/Fa /c", 
                "CK_FLAGS_CREATE_OBJ": "/c", 
                "CK_FLAGS_DLL": "/MT /DWin /LD", 
                "CK_FLAGS_DLL_EXTRA": "/link /dll", 
                "CK_FLAGS_DYNAMIC_BIN": "/MD", 
                "CK_FLAGS_OUTPUT": "/Fe", 
                "CK_FLAGS_STATIC_BIN": "/MT", 
                "CK_FLAGS_STATIC_LIB": "/MD", 
                "CK_FLAG_PREFIX_INCLUDE": "/I", 
                "CK_FLAG_PREFIX_VAR": "/D", 
                "CK_LB": "lib", 
                "CK_LB_OUTPUT": "/OUT:", 
                "CK_LD_DYNAMIC_FLAGS": "/link /NODEFAULTLIB:LIBCMT", 
                "CK_LD_FLAGS_EXTRA": "", 
                "CK_LIB_EXT": ".lib", 
                "CK_MAKE": "nmake", 
                "CK_OBJDUMP": "dumpbin /disasm", 
                "CK_OBJ_EXT": ".obj"
              }, 
              "env_script": "env.bat", 
              "setup": {
                "host_os_uoa": "7a95e0754c37610a", 
                "target_os_bits": "64", 
                "target_os_uoa": "7a95e0754c37610a", 
                "version": "18.00"
              }, 
              "soft_uoa": "a4c8d6c8e946c49f", 
              "tags": [
                "64bits", 
                "compiler", 
                "host-os-windows-64", 
                "lang-c", 
                "lang-cpp", 
                "mcl", 
                "target-os-windows-64", 
                "v18", 
                "v18.00"
              ]
            }, 
            "local": "yes", 
            "num_entries": 1, 
            "tags": "compiler,mcl,v18.00", 
            "uoa": "924e05b4e11f9dcc", 
            "ver": "18.00"
          }
        }, 
        "env": {
          "CK_AR": "lib", 
          "CK_ASM_EXT": ".asm", 
          "CK_CC": "icl", 
          "CK_COMPILER_FLAGS_OBLIGATORY": "/DWINDOWS /GS-", 
          "CK_COMPILER_FLAG_CPP11": "/Qstd=c++11", 
          "CK_COMPILER_FLAG_OPENMP": "/openmp", 
          "CK_COMPILER_FLAG_PTHREAD_LIB": "/pthread", 
          "CK_COMPILER_FLAG_STD90": "/Qstd=c90", 
          "CK_COMPILER_FLAG_STD99": "/Qstd=c99", 
          "CK_CSTD99": "/Qstd=c99", 
          "CK_CXX": "icl", 
          "CK_DLL_EXT": ".dll", 
          "CK_EXE_EXT": ".exe", 
          "CK_EXTRA_LIB_DL": "", 
          "CK_EXTRA_LIB_M": "", 
          "CK_F90": "ifort /fpp", 
          "CK_F95": "ifort /fpp", 
          "CK_FC": "ifort /fpp", 
          "CK_FLAGS_CREATE_ASM": "/Fa /c", 
          "CK_FLAGS_CREATE_OBJ": "/c", 
          "CK_FLAGS_DLL": "/MT /DWin /LD /FIwindows.h", 
          "CK_FLAGS_DLL_EXTRA": "/link /dll", 
          "CK_FLAGS_DYNAMIC_BIN": "/MD", 
          "CK_FLAGS_OUTPUT": "/Fe", 
          "CK_FLAGS_STATIC_BIN": "/MT", 
          "CK_FLAGS_STATIC_LIB": "/MD", 
          "CK_FLAG_PREFIX_INCLUDE": "/I", 
          "CK_FLAG_PREFIX_VAR": "/D", 
          "CK_LB": "lib", 
          "CK_LB_OUTPUT": "/OUT:", 
          "CK_LD_DYNAMIC_FLAGS": "/link /NODEFAULTLIB:LIBCMT", 
          "CK_LD_FLAGS_EXTRA": "bufferoverflowU.lib", 
          "CK_LIB_EXT": ".lib", 
          "CK_MAKE": "nmake", 
          "CK_OBJDUMP": "dumpbin /disasm", 
          "CK_OBJ_EXT": ".obj"
        }, 
        "env_script": "env.bat", 
        "package_uoa": "8ec292a541719523", 
        "setup": {
          "deps_compiler_mcl": "924e05b4e11f9dcc", 
          "host_os_uoa": "7a95e0754c37610a", 
          "target_os_bits": "64", 
          "target_os_uoa": "7a95e0754c37610a", 
          "version": "2015"
        }, 
        "soft_uoa": "f0e7b534fc84d18a", 
        "tags": [
          "64bits", 
          "compiler", 
          "host-os-windows-64", 
          "icc", 
          "lang-c", 
          "lang-cpp", 
          "lang-f77", 
          "lang-f90", 
          "lang-f95", 
          "target-os-windows-64", 
          "v2015"
        ]
      }, 
      "local": "yes", 
      "num_entries": 1, 
      "sort": 10, 
      "tags": "compiler,lang-cpp", 
      "uoa": "289842d618a4e54a", 
      "ver": "2015"
    }, 
    "lib.xopenme": {
      "bat": "call D:\\Work1\\CK\\ck-repos\\fgg-local-win\\env\\ce48085aba489278\\env.bat\n", 
      "choices": [
        "ce48085aba489278"
      ], 
      "cus": {
        "add_include_path": "yes", 
        "dynamic_lib": "librtlxopenme.dll", 
        "env_prefix": "CK_ENV_LIB_RTL_XOPENME", 
        "extra_dir": "", 
        "include_name": "xopenme.h", 
        "path_include": "D:\\!FGG\\Installations\\lib-rtl-xopenme-0.3-icc-2015-windows-64\\include", 
        "path_install": "D:\\!FGG\\Installations\\lib-rtl-xopenme-0.3-icc-2015-windows-64", 
        "path_lib": "D:\\!FGG\\Installations\\lib-rtl-xopenme-0.3-icc-2015-windows-64\\lib", 
        "skip_add_to_bin": "yes", 
        "skip_add_to_path": "yes", 
        "static_lib": "librtlxopenme.lib", 
        "version": "0.3", 
        "version_int": 3
      }, 
      "dict": {
        "customize": {
          "add_include_path": "yes", 
          "dynamic_lib": "librtlxopenme.dll", 
          "env_prefix": "CK_ENV_LIB_RTL_XOPENME", 
          "extra_dir": "", 
          "include_name": "xopenme.h", 
          "path_include": "D:\\!FGG\\Installations\\lib-rtl-xopenme-0.3-icc-2015-windows-64\\include", 
          "path_install": "D:\\!FGG\\Installations\\lib-rtl-xopenme-0.3-icc-2015-windows-64", 
          "path_lib": "D:\\!FGG\\Installations\\lib-rtl-xopenme-0.3-icc-2015-windows-64\\lib", 
          "skip_add_to_bin": "yes", 
          "skip_add_to_path": "yes", 
          "static_lib": "librtlxopenme.lib", 
          "version": "0.3", 
          "version_int": 3
        }, 
        "deps": {
          "compiler": {
            "bat": "call D:\\Work1\\CK\\ck-repos\\fgg-local-win\\env\\289842d618a4e54a\\env.bat\n", 
            "build_dir_name": "icc", 
            "cus": {
              "build-dir-name": "icc", 
              "build_dir_name": "icc", 
              "env_prefix": "CK_ENV_COMPILER_ICC", 
              "extra_dir": "", 
              "languages": [
                "C", 
                "CPP", 
                "F77", 
                "F90", 
                "F95"
              ], 
              "path_install": "C:\\Program Files (x86)\\Intel\\Composer XE 2015", 
              "retarget": "", 
              "skip_add_to_bin": "yes", 
              "skip_add_to_ld_path": "yes", 
              "skip_add_to_path": "yes", 
              "tool_prefix": "", 
              "version": "2015", 
              "version_int": 2015
            }, 
            "dict": {
              "customize": {
                "build-dir-name": "icc", 
                "build_dir_name": "icc", 
                "env_prefix": "CK_ENV_COMPILER_ICC", 
                "extra_dir": "", 
                "languages": [
                  "C", 
                  "CPP", 
                  "F77", 
                  "F90", 
                  "F95"
                ], 
                "path_install": "C:\\Program Files (x86)\\Intel\\Composer XE 2015", 
                "retarget": "", 
                "skip_add_to_bin": "yes", 
                "skip_add_to_ld_path": "yes", 
                "skip_add_to_path": "yes", 
                "tool_prefix": "", 
                "version": "2015", 
                "version_int": 2015
              }, 
              "deps": {
                "compiler_mcl": {
                  "bat": "call D:\\Work1\\CK\\ck-repos\\fgg-local-win\\env\\924e05b4e11f9dcc\\env.bat\n", 
                  "build_dir_name": "mcl", 
                  "dict": {
                    "customize": {
                      "add_win_sdk_path": "yes", 
                      "build-dir-name": "mcl", 
                      "build_dir_name": "mcl", 
                      "env_prefix": "CK_ENV_COMPILER_MVSC", 
                      "extra_dir": "", 
                      "input_path_example": "C:\\Program Files (x86)\\Microsoft Visual Studio 9.0\\VC", 
                      "languages": [
                        "C", 
                        "CPP"
                      ], 
                      "path_install": "C:\\Program Files (x86)\\Microsoft Visual Studio 12.0\\VC", 
                      "retarget": "", 
                      "skip_add_to_bin": "yes", 
                      "skip_add_to_ld_path": "yes", 
                      "skip_add_to_path": "yes", 
                      "tool_prefix": "", 
                      "version": "18.00", 
                      "version_int": 1800
                    }, 
                    "deps": {}, 
                    "env": {
                      "CK_AR": "lib", 
                      "CK_ASM_EXT": ".asm", 
                      "CK_CC": "cl", 
                      "CK_COMPILER_FLAGS_OBLIGATORY": "/DWINDOWS /GS-", 
                      "CK_COMPILER_FLAG_CPP11": "/Qstd=c++11", 
                      "CK_COMPILER_FLAG_OPENMP": "/openmp", 
                      "CK_COMPILER_FLAG_PTHREAD_LIB": "/pthread", 
                      "CK_COMPILER_FLAG_STD90": "/Qstd=c90", 
                      "CK_COMPILER_FLAG_STD99": "/Qstd=c99", 
                      "CK_CXX": "cl", 
                      "CK_DLL_EXT": ".dll", 
                      "CK_EXE_EXT": ".exe", 
                      "CK_FLAGS_CREATE_ASM": "/Fa /c", 
                      "CK_FLAGS_CREATE_OBJ": "/c", 
                      "CK_FLAGS_DLL": "/MT /DWin /LD", 
                      "CK_FLAGS_DLL_EXTRA": "/link /dll", 
                      "CK_FLAGS_DYNAMIC_BIN": "/MD", 
                      "CK_FLAGS_OUTPUT": "/Fe", 
                      "CK_FLAGS_STATIC_BIN": "/MT", 
                      "CK_FLAGS_STATIC_LIB": "/MD", 
                      "CK_FLAG_PREFIX_INCLUDE": "/I", 
                      "CK_FLAG_PREFIX_VAR": "/D", 
                      "CK_LB": "lib", 
                      "CK_LB_OUTPUT": "/OUT:", 
                      "CK_LD_DYNAMIC_FLAGS": "/link /NODEFAULTLIB:LIBCMT", 
                      "CK_LD_FLAGS_EXTRA": "", 
                      "CK_LIB_EXT": ".lib", 
                      "CK_MAKE": "nmake", 
                      "CK_OBJDUMP": "dumpbin /disasm", 
                      "CK_OBJ_EXT": ".obj"
                    }, 
                    "env_script": "env.bat", 
                    "setup": {
                      "host_os_uoa": "7a95e0754c37610a", 
                      "target_os_bits": "64", 
                      "target_os_uoa": "7a95e0754c37610a", 
                      "version": "18.00"
                    }, 
                    "soft_uoa": "a4c8d6c8e946c49f", 
                    "tags": [
                      "64bits", 
                      "compiler", 
                      "host-os-windows-64", 
                      "lang-c", 
                      "lang-cpp", 
                      "mcl", 
                      "target-os-windows-64", 
                      "v18", 
                      "v18.00"
                    ]
                  }, 
                  "local": "yes", 
                  "num_entries": 1, 
                  "tags": "compiler,mcl,v18.00", 
                  "uoa": "924e05b4e11f9dcc", 
                  "ver": "18.00"
                }
              }, 
              "env": {
                "CK_AR": "lib", 
                "CK_ASM_EXT": ".asm", 
                "CK_CC": "icl", 
                "CK_COMPILER_FLAGS_OBLIGATORY": "/DWINDOWS /GS-", 
                "CK_COMPILER_FLAG_CPP11": "/Qstd=c++11", 
                "CK_COMPILER_FLAG_OPENMP": "/openmp", 
                "CK_COMPILER_FLAG_PTHREAD_LIB": "/pthread", 
                "CK_COMPILER_FLAG_STD90": "/Qstd=c90", 
                "CK_COMPILER_FLAG_STD99": "/Qstd=c99", 
                "CK_CSTD99": "/Qstd=c99", 
                "CK_CXX": "icl", 
                "CK_DLL_EXT": ".dll", 
                "CK_EXE_EXT": ".exe", 
                "CK_EXTRA_LIB_DL": "", 
                "CK_EXTRA_LIB_M": "", 
                "CK_F90": "ifort /fpp", 
                "CK_F95": "ifort /fpp", 
                "CK_FC": "ifort /fpp", 
                "CK_FLAGS_CREATE_ASM": "/Fa /c", 
                "CK_FLAGS_CREATE_OBJ": "/c", 
                "CK_FLAGS_DLL": "/MT /DWin /LD /FIwindows.h", 
                "CK_FLAGS_DLL_EXTRA": "/link /dll", 
                "CK_FLAGS_DYNAMIC_BIN": "/MD", 
                "CK_FLAGS_OUTPUT": "/Fe", 
                "CK_FLAGS_STATIC_BIN": "/MT", 
                "CK_FLAGS_STATIC_LIB": "/MD", 
                "CK_FLAG_PREFIX_INCLUDE": "/I", 
                "CK_FLAG_PREFIX_VAR": "/D", 
                "CK_LB": "lib", 
                "CK_LB_OUTPUT": "/OUT:", 
                "CK_LD_DYNAMIC_FLAGS": "/link /NODEFAULTLIB:LIBCMT", 
                "CK_LD_FLAGS_EXTRA": "bufferoverflowU.lib", 
                "CK_LIB_EXT": ".lib", 
                "CK_MAKE": "nmake", 
                "CK_OBJDUMP": "dumpbin /disasm", 
                "CK_OBJ_EXT": ".obj"
              }, 
              "env_script": "env.bat", 
              "package_uoa": "8ec292a541719523", 
              "setup": {
                "deps_compiler_mcl": "924e05b4e11f9dcc", 
                "host_os_uoa": "7a95e0754c37610a", 
                "target_os_bits": "64", 
                "target_os_uoa": "7a95e0754c37610a", 
                "version": "2015"
              }, 
              "soft_uoa": "f0e7b534fc84d18a", 
              "tags": [
                "64bits", 
                "compiler", 
                "host-os-windows-64", 
                "icc", 
                "lang-c", 
                "lang-cpp", 
                "lang-f77", 
                "lang-f90", 
                "lang-f95", 
                "target-os-windows-64", 
                "v2015"
              ]
            }, 
            "local": "yes", 
            "num_entries": 1, 
            "tags": "compiler,lang-c", 
            "uoa": "289842d618a4e54a", 
            "ver": "2015"
          }
        }, 
        "env": {
          "CK_ENV_LIB_RTL_XOPENME_DYNAMIC_NAME": "librtlxopenme.dll", 
          "CK_ENV_LIB_RTL_XOPENME_INCLUDE_NAME": "xopenme.h", 
          "CK_ENV_LIB_RTL_XOPENME_STATIC_NAME": "librtlxopenme.lib"
        }, 
        "env_script": "env.bat", 
        "package_uoa": "0573487b8121d094", 
        "setup": {
          "deps_compiler": "289842d618a4e54a", 
          "host_os_uoa": "7a95e0754c37610a", 
          "target_os_bits": "64", 
          "target_os_uoa": "7a95e0754c37610a", 
          "version": "0.3"
        }, 
        "soft_uoa": "673507878d649b4a", 
        "tags": [
          "64bits", 
          "host-os-windows-64", 
          "lang-c", 
          "lang-cpp", 
          "lang-f77", 
          "lang-f90", 
          "lang-f95", 
          "lib", 
          "rtl", 
          "target-os-windows-64", 
          "v0", 
          "v0.3", 
          "xopenme"
        ]
      }, 
      "local": "yes", 
      "num_entries": 1, 
      "sort": 40, 
      "tags": "lib,xopenme", 
      "uoa": "ce48085aba489278", 
      "ver": "0.3"
    }, 
    "lib_opencl": {
      "bat": "call D:\\Work1\\CK\\ck-repos\\fgg-local-win\\env\\de433cac44b1c0f7\\env.bat\n", 
      "choices": [
        "de433cac44b1c0f7"
      ], 
      "cus": {
        "add_include_path": "yes", 
        "env_prefix": "CK_ENV_LIB_OPENCL", 
        "include_name": "CL\\opencl.h", 
        "path_bin": "C:\\Program Files (x86)\\Intel\\OpenCL SDK\\4.6\\bin\\x64", 
        "path_include": "C:\\Program Files (x86)\\Intel\\OpenCL SDK\\4.6\\include", 
        "path_install": "C:\\Program Files (x86)\\Intel\\OpenCL SDK\\4.6", 
        "path_lib": "C:\\Program Files (x86)\\Intel\\OpenCL SDK\\4.6\\lib\\x64", 
        "skip_add_to_ld_path": "yes", 
        "static_lib": "OpenCL.lib", 
        "version": "4.6", 
        "version_int": 406
      }, 
      "dict": {
        "customize": {
          "add_include_path": "yes", 
          "env_prefix": "CK_ENV_LIB_OPENCL", 
          "include_name": "CL\\opencl.h", 
          "path_bin": "C:\\Program Files (x86)\\Intel\\OpenCL SDK\\4.6\\bin\\x64", 
          "path_include": "C:\\Program Files (x86)\\Intel\\OpenCL SDK\\4.6\\include", 
          "path_install": "C:\\Program Files (x86)\\Intel\\OpenCL SDK\\4.6", 
          "path_lib": "C:\\Program Files (x86)\\Intel\\OpenCL SDK\\4.6\\lib\\x64", 
          "skip_add_to_ld_path": "yes", 
          "static_lib": "OpenCL.lib", 
          "version": "4.6", 
          "version_int": 406
        }, 
        "deps": {}, 
        "env": {
          "CK_ENV_LIB_OPENCL_DYNAMIC_NAME": "", 
          "CK_ENV_LIB_OPENCL_INCLUDE_NAME": "CL\\opencl.h", 
          "CK_ENV_LIB_OPENCL_STATIC_NAME": "OpenCL.lib"
        }, 
        "env_script": "env.bat", 
        "setup": {
          "host_os_uoa": "7a95e0754c37610a", 
          "target_os_bits": "64", 
          "target_os_uoa": "7a95e0754c37610a", 
          "version": "4.6"
        }, 
        "soft_uoa": "b13b6a18695c3675", 
        "tags": [
          "64bits", 
          "host-os-windows-64", 
          "intel", 
          "lib", 
          "opencl", 
          "target-os-windows-64", 
          "v4", 
          "v4.6"
        ]
      }, 
      "local": "yes", 
      "num_entries": 1, 
      "sort": 30, 
      "tags": "lib,opencl", 
      "uoa": "de433cac44b1c0f7", 
      "ver": "4.6"
    }, 
    "lib_opencv": {
      "bat": "call D:\\Work1\\CK\\ck-repos\\fgg-local-win\\env\\4d4186ee57672b1e\\env.bat\n", 
      "choices": [
        "4d4186ee57672b1e"
      ], 
      "cus": {
        "add_include_path": "yes", 
        "dynamic_lib": "opencv_core2411d.dll", 
        "env_prefix": "CK_ENV_LIB_OPENCV", 
        "extra_dir": "build\\install", 
        "extra_dynamic_libs": {
          "opencv_highgui": "opencv_highgui2411d.dll", 
          "opencv_imgproc": "opencv_imgproc2411d.dll", 
          "opencv_ocl": "opencv_ocl2411d.dll"
        }, 
        "extra_static_libs": {
          "opencv_highgui": "opencv_highgui2411d.lib", 
          "opencv_imgproc": "opencv_imgproc2411d.lib", 
          "opencv_ocl": "opencv_ocl2411d.lib"
        }, 
        "lib_extension": "2411d", 
        "lib_extension_configured": "yes", 
        "path_bin": "D:\\!FGG\\Installations\\lib-opencv-2.4.11-mcl-18.00-windows-64\\build\\install\\x64\\vc12\\bin", 
        "path_dynamic_lib": "D:\\!FGG\\Installations\\lib-opencv-2.4.11-mcl-18.00-windows-64\\build\\install\\x64\\vc12\\bin", 
        "path_extension": "vc12", 
        "path_extension_configured": "yes", 
        "path_include": "D:\\!FGG\\Installations\\lib-opencv-2.4.11-mcl-18.00-windows-64\\build\\install\\include", 
        "path_install": "D:\\!FGG\\Installations\\lib-opencv-2.4.11-mcl-18.00-windows-64\\build\\install", 
        "path_lib": "D:\\!FGG\\Installations\\lib-opencv-2.4.11-mcl-18.00-windows-64\\build\\install\\x64\\vc12\\lib", 
        "path_static_lib": "D:\\!FGG\\Installations\\lib-opencv-2.4.11-mcl-18.00-windows-64\\build\\install\\x64\\vc12\\lib", 
        "skip_add_to_ld_path": "yes", 
        "static_lib": "opencv_core2411d.lib", 
        "version": "2.4.11", 
        "version_int": 20411
      }, 
      "dict": {
        "customize": {
          "add_include_path": "yes", 
          "dynamic_lib": "opencv_core2411d.dll", 
          "env_prefix": "CK_ENV_LIB_OPENCV", 
          "extra_dir": "build\\install", 
          "extra_dynamic_libs": {
            "opencv_highgui": "opencv_highgui2411d.dll", 
            "opencv_imgproc": "opencv_imgproc2411d.dll", 
            "opencv_ocl": "opencv_ocl2411d.dll"
          }, 
          "extra_static_libs": {
            "opencv_highgui": "opencv_highgui2411d.lib", 
            "opencv_imgproc": "opencv_imgproc2411d.lib", 
            "opencv_ocl": "opencv_ocl2411d.lib"
          }, 
          "lib_extension": "2411d", 
          "lib_extension_configured": "yes", 
          "path_bin": "D:\\!FGG\\Installations\\lib-opencv-2.4.11-mcl-18.00-windows-64\\build\\install\\x64\\vc12\\bin", 
          "path_dynamic_lib": "D:\\!FGG\\Installations\\lib-opencv-2.4.11-mcl-18.00-windows-64\\build\\install\\x64\\vc12\\bin", 
          "path_extension": "vc12", 
          "path_extension_configured": "yes", 
          "path_include": "D:\\!FGG\\Installations\\lib-opencv-2.4.11-mcl-18.00-windows-64\\build\\install\\include", 
          "path_install": "D:\\!FGG\\Installations\\lib-opencv-2.4.11-mcl-18.00-windows-64\\build\\install", 
          "path_lib": "D:\\!FGG\\Installations\\lib-opencv-2.4.11-mcl-18.00-windows-64\\build\\install\\x64\\vc12\\lib", 
          "path_static_lib": "D:\\!FGG\\Installations\\lib-opencv-2.4.11-mcl-18.00-windows-64\\build\\install\\x64\\vc12\\lib", 
          "skip_add_to_ld_path": "yes", 
          "static_lib": "opencv_core2411d.lib", 
          "version": "2.4.11", 
          "version_int": 20411
        }, 
        "deps": {
          "cmake": {
            "bat": "call D:\\Work1\\CK\\ck-repos\\fgg-local-win\\env\\4b201441c6ae66b0\\env.bat\n", 
            "dict": {
              "customize": {
                "env_prefix": "CK_ENV_TOOL_CMAKE", 
                "extra_dir": "cmake-3.1.3-win32-x86", 
                "linking_for_retargeting": "", 
                "path_bin": "D:\\!FGG\\Installations\\cmake-3.1.3\\cmake-3.1.3-win32-x86\\bin", 
                "path_install": "D:\\!FGG\\Installations\\cmake-3.1.3\\cmake-3.1.3-win32-x86", 
                "skip_add_to_ld_path": "yes", 
                "tool_prefix": "", 
                "version": "3.1.3", 
                "version_int": 30103
              }, 
              "deps": {}, 
              "env": {
                "CK_CMAKE": "cmake"
              }, 
              "env_script": "env.bat", 
              "setup": {
                "host_os_uoa": "7a95e0754c37610a", 
                "target_os_bits": "64", 
                "target_os_uoa": "7a95e0754c37610a", 
                "version": "3.1.3"
              }, 
              "soft_uoa": "77ef5e31404d9589", 
              "tags": [
                "64bits", 
                "cmake", 
                "host-os-windows-64", 
                "target-os-windows-64", 
                "tool", 
                "v3", 
                "v3.1", 
                "v3.1.3"
              ]
            }, 
            "local": "yes", 
            "num_entries": 1, 
            "skip_from_bat": "yes", 
            "tags": "tool,cmake", 
            "uoa": "4b201441c6ae66b0", 
            "ver": "3.1.3"
          }, 
          "compiler": {
            "bat": "call D:\\Work1\\CK\\ck-repos\\fgg-local-win\\env\\924e05b4e11f9dcc\\env.bat\n", 
            "build_dir_name": "mcl", 
            "dict": {
              "customize": {
                "add_win_sdk_path": "yes", 
                "build-dir-name": "mcl", 
                "build_dir_name": "mcl", 
                "env_prefix": "CK_ENV_COMPILER_MVSC", 
                "extra_dir": "", 
                "input_path_example": "C:\\Program Files (x86)\\Microsoft Visual Studio 9.0\\VC", 
                "languages": [
                  "C", 
                  "CPP"
                ], 
                "path_install": "C:\\Program Files (x86)\\Microsoft Visual Studio 12.0\\VC", 
                "retarget": "", 
                "skip_add_to_bin": "yes", 
                "skip_add_to_ld_path": "yes", 
                "skip_add_to_path": "yes", 
                "tool_prefix": "", 
                "version": "18.00", 
                "version_int": 1800
              }, 
              "deps": {}, 
              "env": {
                "CK_AR": "lib", 
                "CK_ASM_EXT": ".asm", 
                "CK_CC": "cl", 
                "CK_COMPILER_FLAGS_OBLIGATORY": "/DWINDOWS /GS-", 
                "CK_COMPILER_FLAG_CPP11": "/Qstd=c++11", 
                "CK_COMPILER_FLAG_OPENMP": "/openmp", 
                "CK_COMPILER_FLAG_PTHREAD_LIB": "/pthread", 
                "CK_COMPILER_FLAG_STD90": "/Qstd=c90", 
                "CK_COMPILER_FLAG_STD99": "/Qstd=c99", 
                "CK_CXX": "cl", 
                "CK_DLL_EXT": ".dll", 
                "CK_EXE_EXT": ".exe", 
                "CK_FLAGS_CREATE_ASM": "/Fa /c", 
                "CK_FLAGS_CREATE_OBJ": "/c", 
                "CK_FLAGS_DLL": "/MT /DWin /LD", 
                "CK_FLAGS_DLL_EXTRA": "/link /dll", 
                "CK_FLAGS_DYNAMIC_BIN": "/MD", 
                "CK_FLAGS_OUTPUT": "/Fe", 
                "CK_FLAGS_STATIC_BIN": "/MT", 
                "CK_FLAGS_STATIC_LIB": "/MD", 
                "CK_FLAG_PREFIX_INCLUDE": "/I", 
                "CK_FLAG_PREFIX_VAR": "/D", 
                "CK_LB": "lib", 
                "CK_LB_OUTPUT": "/OUT:", 
                "CK_LD_DYNAMIC_FLAGS": "/link /NODEFAULTLIB:LIBCMT", 
                "CK_LD_FLAGS_EXTRA": "", 
                "CK_LIB_EXT": ".lib", 
                "CK_MAKE": "nmake", 
                "CK_OBJDUMP": "dumpbin /disasm", 
                "CK_OBJ_EXT": ".obj"
              }, 
              "env_script": "env.bat", 
              "setup": {
                "host_os_uoa": "7a95e0754c37610a", 
                "target_os_bits": "64", 
                "target_os_uoa": "7a95e0754c37610a", 
                "version": "18.00"
              }, 
              "soft_uoa": "a4c8d6c8e946c49f", 
              "tags": [
                "64bits", 
                "compiler", 
                "host-os-windows-64", 
                "lang-c", 
                "lang-cpp", 
                "mcl", 
                "target-os-windows-64", 
                "v18", 
                "v18.00"
              ]
            }, 
            "local": "yes", 
            "num_entries": 1, 
            "skip_from_bat": "yes", 
            "tags": "compiler,lang-c,mcl", 
            "uoa": "924e05b4e11f9dcc", 
            "ver": "18.00"
          }, 
          "opencl": {
            "bat": "call D:\\Work1\\CK\\ck-repos\\fgg-local-win\\env\\de433cac44b1c0f7\\env.bat\n", 
            "dict": {
              "customize": {
                "add_include_path": "yes", 
                "env_prefix": "CK_ENV_LIB_OPENCL", 
                "include_name": "CL\\opencl.h", 
                "path_bin": "C:\\Program Files (x86)\\Intel\\OpenCL SDK\\4.6\\bin\\x64", 
                "path_include": "C:\\Program Files (x86)\\Intel\\OpenCL SDK\\4.6\\include", 
                "path_install": "C:\\Program Files (x86)\\Intel\\OpenCL SDK\\4.6", 
                "path_lib": "C:\\Program Files (x86)\\Intel\\OpenCL SDK\\4.6\\lib\\x64", 
                "skip_add_to_ld_path": "yes", 
                "static_lib": "OpenCL.lib", 
                "version": "4.6", 
                "version_int": 406
              }, 
              "deps": {}, 
              "env": {
                "CK_ENV_LIB_OPENCL_DYNAMIC_NAME": "", 
                "CK_ENV_LIB_OPENCL_INCLUDE_NAME": "CL\\opencl.h", 
                "CK_ENV_LIB_OPENCL_STATIC_NAME": "OpenCL.lib"
              }, 
              "env_script": "env.bat", 
              "setup": {
                "host_os_uoa": "7a95e0754c37610a", 
                "target_os_bits": "64", 
                "target_os_uoa": "7a95e0754c37610a", 
                "version": "4.6"
              }, 
              "soft_uoa": "b13b6a18695c3675", 
              "tags": [
                "64bits", 
                "host-os-windows-64", 
                "intel", 
                "lib", 
                "opencl", 
                "target-os-windows-64", 
                "v4", 
                "v4.6"
              ]
            }, 
            "local": "yes", 
            "num_entries": 1, 
            "skip_from_bat": "yes", 
            "tags": "lib,opencl", 
            "uoa": "de433cac44b1c0f7", 
            "ver": "4.6"
          }, 
          "tbb": {
            "bat": "call D:\\Work1\\CK\\ck-repos\\fgg-local-win\\env\\7f0942428d7790d4\\env.bat\n", 
            "dict": {
              "customize": {
                "add_include_path": "yes", 
                "dynamic_lib": "libtbb.dll", 
                "env_prefix": "CK_ENV_LIB_TBB", 
                "extra_dir": "tbb43_20150424oss", 
                "extra_dynamic_libs": {
                  "libtbbmalloc": "tbb.dll", 
                  "libtbbproxy": "tbbproxy.dll"
                }, 
                "extra_static_libs": {
                  "libtbbmalloc": "tbbmalloc.lib", 
                  "libtbbproxy": "tbbproxy.lib"
                }, 
                "path_bin": "D:\\!FGG\\Installations\\lib-tbb-4.3-windows-64\\tbb43_20150424oss\\bin\\intel64\\vc12", 
                "path_include": "D:\\!FGG\\Installations\\lib-tbb-4.3-windows-64\\tbb43_20150424oss\\include", 
                "path_install": "D:\\!FGG\\Installations\\lib-tbb-4.3-windows-64\\tbb43_20150424oss", 
                "path_lib": "D:\\!FGG\\Installations\\lib-tbb-4.3-windows-64\\tbb43_20150424oss\\lib\\intel64\\vc12", 
                "skip_add_to_ld_path": "yes", 
                "static_lib": "tbb.lib", 
                "version": "4.3", 
                "version_int": 403, 
                "visual_studio_compiler": "vc12", 
                "visual_studio_compiler_configured": "yes"
              }, 
              "deps": {}, 
              "env": {}, 
              "env_script": "env.bat", 
              "setup": {
                "host_os_uoa": "7a95e0754c37610a", 
                "target_os_bits": "64", 
                "target_os_uoa": "7a95e0754c37610a", 
                "version": "4.3"
              }, 
              "soft_uoa": "fe71b1243e6bb329", 
              "tags": [
                "64bits", 
                "host-os-windows-64", 
                "intel", 
                "lib", 
                "target-os-windows-64", 
                "tbb", 
                "v4", 
                "v4.3"
              ]
            }, 
            "local": "yes", 
            "num_entries": 1, 
            "tags": "lib,tbb", 
            "uoa": "7f0942428d7790d4", 
            "ver": "4.3"
          }
        }, 
        "env": {
          "CK_ENV_LIB_OPENCV_DYNAMIC_LIB_PATH": "D:\\!FGG\\Installations\\lib-opencv-2.4.11-mcl-18.00-windows-64\\build\\install\\x64\\vc12\\bin", 
          "CK_ENV_LIB_OPENCV_STATIC_LIB_PATH": "D:\\!FGG\\Installations\\lib-opencv-2.4.11-mcl-18.00-windows-64\\build\\install\\x64\\vc12\\lib"
        }, 
        "env_script": "env.bat", 
        "package_uoa": "edcaeb00453e8f52", 
        "setup": {
          "deps_cmake": "4b201441c6ae66b0", 
          "deps_compiler": "924e05b4e11f9dcc", 
          "deps_opencl": "de433cac44b1c0f7", 
          "deps_tbb": "7f0942428d7790d4", 
          "host_os_uoa": "7a95e0754c37610a", 
          "target_os_bits": "64", 
          "target_os_uoa": "7a95e0754c37610a", 
          "version": "2.4.11"
        }, 
        "soft_uoa": "18eb79fe079438fb", 
        "tags": [
          "64bits", 
          "host-os-windows-64", 
          "lib", 
          "opencv", 
          "target-os-windows-64", 
          "v2", 
          "v2.4", 
          "v2.4.11"
        ]
      }, 
      "extra_libs": [
        "opencv_imgproc", 
        "opencv_ocl", 
        "opencv_highgui"
      ], 
      "local": "yes", 
      "num_entries": 1, 
      "sort": 20, 
      "tags": "lib,opencv", 
      "uoa": "4d4186ee57672b1e", 
      "ver": "2.4.11"
    }, 
    "lib_tbb": {
      "bat": "call D:\\Work1\\CK\\ck-repos\\fgg-local-win\\env\\7f0942428d7790d4\\env.bat\n", 
      "choices": [
        "7f0942428d7790d4"
      ], 
      "cus": {
        "add_include_path": "yes", 
        "dynamic_lib": "libtbb.dll", 
        "env_prefix": "CK_ENV_LIB_TBB", 
        "extra_dir": "tbb43_20150424oss", 
        "extra_dynamic_libs": {
          "libtbbmalloc": "tbb.dll", 
          "libtbbproxy": "tbbproxy.dll"
        }, 
        "extra_static_libs": {
          "libtbbmalloc": "tbbmalloc.lib", 
          "libtbbproxy": "tbbproxy.lib"
        }, 
        "path_bin": "D:\\!FGG\\Installations\\lib-tbb-4.3-windows-64\\tbb43_20150424oss\\bin\\intel64\\vc12", 
        "path_include": "D:\\!FGG\\Installations\\lib-tbb-4.3-windows-64\\tbb43_20150424oss\\include", 
        "path_install": "D:\\!FGG\\Installations\\lib-tbb-4.3-windows-64\\tbb43_20150424oss", 
        "path_lib": "D:\\!FGG\\Installations\\lib-tbb-4.3-windows-64\\tbb43_20150424oss\\lib\\intel64\\vc12", 
        "skip_add_to_ld_path": "yes", 
        "static_lib": "tbb.lib", 
        "version": "4.3", 
        "version_int": 403, 
        "visual_studio_compiler": "vc12", 
        "visual_studio_compiler_configured": "yes"
      }, 
      "dict": {
        "customize": {
          "add_include_path": "yes", 
          "dynamic_lib": "libtbb.dll", 
          "env_prefix": "CK_ENV_LIB_TBB", 
          "extra_dir": "tbb43_20150424oss", 
          "extra_dynamic_libs": {
            "libtbbmalloc": "tbb.dll", 
            "libtbbproxy": "tbbproxy.dll"
          }, 
          "extra_static_libs": {
            "libtbbmalloc": "tbbmalloc.lib", 
            "libtbbproxy": "tbbproxy.lib"
          }, 
          "path_bin": "D:\\!FGG\\Installations\\lib-tbb-4.3-windows-64\\tbb43_20150424oss\\bin\\intel64\\vc12", 
          "path_include": "D:\\!FGG\\Installations\\lib-tbb-4.3-windows-64\\tbb43_20150424oss\\include", 
          "path_install": "D:\\!FGG\\Installations\\lib-tbb-4.3-windows-64\\tbb43_20150424oss", 
          "path_lib": "D:\\!FGG\\Installations\\lib-tbb-4.3-windows-64\\tbb43_20150424oss\\lib\\intel64\\vc12", 
          "skip_add_to_ld_path": "yes", 
          "static_lib": "tbb.lib", 
          "version": "4.3", 
          "version_int": 403, 
          "visual_studio_compiler": "vc12", 
          "visual_studio_compiler_configured": "yes"
        }, 
        "deps": {}, 
        "env": {}, 
        "env_script": "env.bat", 
        "setup": {
          "host_os_uoa": "7a95e0754c37610a", 
          "target_os_bits": "64", 
          "target_os_uoa": "7a95e0754c37610a", 
          "version": "4.3"
        }, 
        "soft_uoa": "fe71b1243e6bb329", 
        "tags": [
          "64bits", 
          "host-os-windows-64", 
          "intel", 
          "lib", 
          "target-os-windows-64", 
          "tbb", 
          "v4", 
          "v4.3"
        ]
      }, 
      "local": "yes", 
      "num_entries": 1, 
      "sort": 50, 
      "tags": "lib,tbb", 
      "uoa": "7f0942428d7790d4", 
      "ver": "4.3"
    }
  }, 
  "fail": "no", 
  "features": {
    "compiler_version": {
      "list": [
        "15", 
        "0", 
        "1", 
        "148"
      ], 
      "raw": [
        "Intel(R) C++ Intel(R) 64 Compiler XE for applications running on Intel(R) 64, Version 15.0.1.148 Build 20141023", 
        "Copyright (C) 1985-2014 Intel Corporation.  All rights reserved.", 
        "", 
        "icl: command line error: no files specified; for help type \"icl /help\"", 
        ""
      ], 
      "str": "15.0.1.148"
    }
  }, 
  "ready": "yes", 
  "speed": "yes", 
  "state": {
    "cur_dir": "D:\\Work1\\CK\\ck-repos\\reproduce-carp-project\\demo\\explore-hog-compilers", 
    "tmp_dir": "tmp"
  }
}
